e3dc/_RSCPEncryptDecrypt.py
e3dc/__init__.py
e3dc/_e3dc.py
e3dc/_e3dc_rscp_local.py
e3dc/_e3dc_rscp_web.py
e3dc/_rscpLib.py
e3dc/_rscpTags.py
e3dc/py.typed
pye3dc-0.9.2.dist-info/AUTHORS
pye3dc-0.9.2.dist-info/LICENSE
pye3dc-0.9.2.dist-info/METADATA
pye3dc-0.9.2.dist-info/WHEEL
pye3dc-0.9.2.dist-info/top_level.txt
pye3dc-0.9.2.dist-info/RECORD
