Metadata-Version: 2.1
Name: pye3dc
Version: 0.9.2
Summary: E3/DC client for python
Author-email: Francesco Santini <francesco.santini@gmail.com>, Christopher Banck <christopher@banck.net>
License: MIT
Project-URL: Documentation, https://python-e3dc.readthedocs.io
Project-URL: Repository, https://github.com/fsantini/python-e3dc
Classifier: Development Status :: 4 - Beta
Classifier: Environment :: Web Environment
Classifier: Environment :: Console
Classifier: Intended Audience :: Developers
Classifier: License :: OSI Approved :: MIT License
Classifier: Operating System :: OS Independent
Classifier: Programming Language :: Python :: 3.8
Classifier: Programming Language :: Python :: 3.9
Classifier: Programming Language :: Python :: 3.10
Classifier: Programming Language :: Python :: 3.11
Classifier: Programming Language :: Python :: 3.12
Requires-Python: >=3.8
License-File: LICENSE
License-File: AUTHORS
Requires-Dist: py3rijndael
Requires-Dist: python-dateutil
Requires-Dist: tzlocal
Requires-Dist: websocket-client
Provides-Extra: develop
Requires-Dist: jsbeautifier ; extra == 'develop'
Requires-Dist: argparse ; extra == 'develop'
Requires-Dist: docker ; extra == 'develop'
Requires-Dist: black ; extra == 'develop'
Requires-Dist: isort ; extra == 'develop'
Requires-Dist: flake8 ; extra == 'develop'
Requires-Dist: flake8-docstrings ; extra == 'develop'
Requires-Dist: flake8-pyproject ; extra == 'develop'
Requires-Dist: pyright ; extra == 'develop'
